weibo_photos/__init__.py
weibo_photos/app.py
weibo_photos/auth.py
weibo_photos/db.py
weibo_photos/weibo_images_crawler.py
weibo_photos-0.3.4.dist-info/LICENSE
weibo_photos-0.3.4.dist-info/METADATA
weibo_photos-0.3.4.dist-info/WHEEL
weibo_photos-0.3.4.dist-info/entry_points.txt
weibo_photos-0.3.4.dist-info/top_level.txt
weibo_photos-0.3.4.dist-info/RECORD
