Metadata-Version: 2.1
Name: weibo-photos
Version: 0.3.4
Summary: Download Weibo photos
Home-page: https://github.com/darknoll/weibo_image_crawler
Author: darknoll
Author-email: darknoll@126.com
License: MIT
Platform: UNKNOWN
Classifier: Programming Language :: Python :: 3.6
Classifier: License :: OSI Approved :: MIT License
Classifier: Operating System :: OS Independent
Requires-Dist: requests (==2.21.0)
Requires-Dist: click (==7.0)
Requires-Dist: rsa (==4.0)
